pybridgeclient.py
pybridgeclient-0.1.0.dist-info/LICENSE.md
pybridgeclient-0.1.0.dist-info/METADATA
pybridgeclient-0.1.0.dist-info/WHEEL
pybridgeclient-0.1.0.dist-info/RECORD
