Metadata-Version: 2.1
Name: pybridgeclient
Version: 0.1.0
Summary: A Python package for interacting with APIs using OpenAPI schema.
Home-page: https://github.com/sinantan/pybridge
License: MIT
Author: sinan tan
Author-email: sinantanwork@gmail.com
Requires-Python: >=3.11,<4.0
Classifier: License :: OSI Approved :: MIT License
Classifier: Programming Language :: Python :: 3
Classifier: Programming Language :: Python :: 3.11
Classifier: Programming Language :: Python :: 3.12
Requires-Dist: requests (>=2.32.3,<3.0.0)
Project-URL: Documentation, https://pybridge.readthedocs.io
Project-URL: Repository, https://github.com/sinantan/pybridge
